__init__.py
consentiumthings.py
micropython_consentiumthings-0.1.6.dist-info/LICENSE
micropython_consentiumthings-0.1.6.dist-info/METADATA
micropython_consentiumthings-0.1.6.dist-info/WHEEL
micropython_consentiumthings-0.1.6.dist-info/top_level.txt
micropython_consentiumthings-0.1.6.dist-info/RECORD
