Metadata-Version: 2.1
Name: micropython-consentiumthings
Version: 0.1.6
Summary: A micropython package for IoT
Author-email: Debjyoti Chowdhury <consentium.inc@gmail.com>
Project-URL: Homepage, https://github.com/
Project-URL: Bug Tracker, https://github.com/pypa/sampleproject/issues
Classifier: Programming Language :: Python :: 3
Classifier: License :: OSI Approved :: MIT License
Classifier: Operating System :: OS Independent
Requires-Python: >=3.7
License-File: LICENSE
